{
	"id" : "10.115.9",
	"classification" : {
		"mandala" : "10",
		"sukta" : "115",
		"ashtaka" : "8",
		"adhyaya" : "6",
		"varga" : "19",
		"anuvaka" : "10",
		"rik" : "9"
	},
	"attribute" : {
		"devata" : "अग्निः",
		"rishi" : "उपस्तुतो वार्ष्टिहव्यः",
		"chandas" : "शक्वरी"
	},
	"samhita" : {
		"lines" : [
			"इ{0}ति{2} त्वा{0}ग्ने{0} वृ{0}ष्थि{1}ह{0}व्य{2}स्य{0} पु{1}त्रा{0} उ{2}प{0}स्तु{1}ता{0}स{1} ऋ{0}ष{2}यो{5}वो{0}च{0}न्{0}",
			"ता{4}श्च{2} पा{1}हि{0} गृ{2}ण{1}त{0}श्च{2} सू{1}री{0}न्व{0}ष{1}ड्व{0}ष{1}ळि{0}त्यू{1}र्ध्वा{0}सो{2} अ{0}न{0}क्ष{1}न्न{0}मो{1} न{0}म{1} इ{0}त्यू{1}र्ध्वा{0}सो{2} अ{0}न{0}क्ष{0}न्{0}"
		]
	},
	"samhitaAux" : {
		"lines" : [
			"इति{2} त्वाग्ने वृष्टि{1}हव्य{2}स्य पु{1}त्रा उ{2}पस्तु{1}तास{1} ऋष{2}यो{5}वोचन् ।",
			"ता{4}श्च{2} पा{1}हि गृ{2}ण{1}तश्च{2} सू{1}रीन्वष{1}ड्वष{1}ळित्यू{1}र्ध्वासो{2} अनक्ष{1}न्नमो{1} नम{1} इत्यू{1}र्ध्वासो{2} अनक्षन् ॥"
		]
	},
	"padapaatha" : {
		"lines" : [
			"इति{2} । त्वा{1} । अ{1}ग्ने{1} । वृ{1}ष्टि{1}{5}हव्य{2}स्य । पु{1}त्राः । उ{1}प{1}{5}स्तु{1}तासः{2} । ऋष{2}यः । अ{1}वो{1}च{1}न् ।",
			"तान् । च{1} । पा{1}हि । गृ{1}ण{1}तः । च{1} । सू{1}रीन् । वष{2}ट् । वष{2}ट् । इति{2} । ऊ{1}र्ध्वासः{2} । अ{1}न{1}क्ष{1}न् । नमः{2} । नमः{2} । इति{2} । ऊ{1}र्ध्वासः{2} । अ{1}न{1}क्ष{1}न् ॥"
		]
	},
	"sayanaBhashya" : "<p>हे अग्ने त्वा त्वामित्येवमुक्तप्रकारेन व्रुष्टिहव्यस्यैतन्नामकस्यर्षेः पुत्रा उप्ततुतास उपस्तुता एतदभिधाना ऋषयः सूक्तद्रष्टारोऽवोचन्। अभ्यष्टुअवन्। तानृषींश्च त्वं पाहि । रक्ष। चवायोगे प्रथमेति न निघातः। तथा गृणतह् स्तोतृण् सूरिन्विदुषश्च पाहि। वषड्वषडिति मन्त्रेणोर्ध्वासो हविष्प्रदानार्थमूर्ध्वमुख हस्ताः सन्तोऽनक्षन्। व्याप्नुवन्। नक्षतिर्व्याप्तिकर्मा। नमो नम इत्येवमूर्थ्वासः स्तोतुमुद्युक्ता अनक्षतन्। य उक्तगुणास्तानुभयविधान्यष्टॄन् स्तोत्रॄन्पालय॥९॥</p>"
}
