{
	"id" : "10.47.7",
	"classification" : {
		"mandala" : "10",
		"sukta" : "47",
		"ashtaka" : "8",
		"adhyaya" : "1",
		"varga" : "4",
		"anuvaka" : "4",
		"rik" : "7"
	},
	"attribute" : {
		"devata" : "इंद्रो वैकुंठः",
		"rishi" : "सप्तगुः",
		"chandas" : "त्रिष्टुप्"
	},
	"samhita" : {
		"lines" : [
			"व{0}नी{2}वा{0}नो{1} म{0}म{2} दू{1}ता{0}स{1} इं{0}द्रं{1} स्तो{0}मा{2}श्च{0}रं{0}ति{0} सु{0}म{1}ती{0}रि{2}या{1}नाः{0}",
			"हृ{1}दि{1}स्पृ{0}शो{1} म{0}न{2}सा{0} व{1}च्य{0}मा{2}ना{0} अ{1}स्म{0}भ्यं{2} चि{1}त्रं{0} वृ{0}ष{2}णं{0} र{1}यिं{0} दाः{2}"
		]
	},
	"samhitaAux" : {
		"lines" : [
			"वनी{2}वानो{1} मम{2} दू{1}तास{1} इन्द्रं{1} स्तोमा{2}श्चरन्ति सुम{1}तीरि{2}या{1}नाः ।",
			"हृ{1}दि{1}स्पृशो{1} मन{2}सा व{1}च्यमा{2}ना अ{1}स्मभ्यं{2} चि{1}त्रं वृष{2}णं र{1}यिं दा{2}ः ॥"
		]
	},
	"padapaatha" : {
		"lines" : [
			"वनी{2}वानः । मम{2} । दू{1}तासः{2} । इन्द्र{2}म् । सोमाः{2} । च{1}र{1}न्ति{1} । सु{1}{5}म{1}तीः । इ{1}या{1}नाः ।",
			"हृ{1}दि{1}{5}स्पृशः{2} । मन{2}सा । व{1}च्यमा{2}नाः । अ{1}स्मभ्य{2}म् । चि{1}त्रम् । वृष{2}णम् । र{1}यिम् । दाः{1} ॥"
		]
	},
	"sayanaBhashya" : "<p>वनीवानो वननवन्तः। छन्दसीवनिपाविति मत्वर्थीयोवनिप्। मम सप्तगोर्दूतासो दूतसदृशाः दूता यथा भर्तुरभिमतार्थं प्रापणीयं प्रापयन्ति तद्वत्स्तुत्यान्गुणान्प्रापयन्तः स्तोमाः स्तवाः सुमतीस्तस्येन्द्रस्यास्मद्विषया अनुकूला बुद्धीरियाना याचमाना इन्द्रं चरन्ति। प्राप्नुवन्ति। पुनश्च त एव विशेष्यन्ते। हृदिस्पृशो हृदये स्पृशन्तः। स्तुत्यस्य प्रियभूता इत्यर्थः। हृद्द्युभ्यामित्युपसङ्ख्यानात् ङेरलुक्। मनसा सत्त्वोद्रिक्तेन वच्यमाना उच्यमानाः। अस्मभ्यमित्यादि गतम्॥७॥</p>"
}
