{
	"id" : "10.33.3",
	"classification" : {
		"mandala" : "10",
		"sukta" : "33",
		"ashtaka" : "7",
		"adhyaya" : "8",
		"varga" : "1",
		"anuvaka" : "3",
		"rik" : "3"
	},
	"attribute" : {
		"devata" : "इंद्रः",
		"rishi" : "कवष ऐलूषः",
		"chandas" : "सतो बृहती"
	},
	"samhita" : {
		"lines" : [
			"मू{0}षो{1} न{0} शि{1}श्ना{0} व्य{2}दं{0}ति{0} मा{1}ध्य{2} स्तो{1}ता{0}रं{2} ते{0} श{0}त{0}क्र{0}तो{0}",
			"स{1}कृ{0}त्सु{0} नो{2} म{0}घ{0}व{0}न्निं{0}द्र{0} मृ{0}ळ{1}या{0}धा{2} पि{1}ते{0}व{2} नो{0} भ{0}व{0}"
		]
	},
	"samhitaAux" : {
		"lines" : [
			"मूषो{1} न शि{1}श्ना व्य{2}दन्ति मा{1}ध्य{2}ः स्तो{1}तारं{2} ते शतक्रतो ।",
			"स{1}कृत्सु नो{2} मघवन्निन्द्र मृळ{1}याधा{2} पि{1}तेव{2} नो भव ॥"
		]
	},
	"padapaatha" : {
		"lines" : [
			"मूषः{2} । न । शि{1}श्ना । वि । अ{1}द{1}न्ति{1} । मा{1} । आ{1}{5}ध्यः{2} । स्तो{1}तार{2}म् । ते{1} । श{1}त{1}क्र{1}तो{1} इति{2} शत{5}क्रतो ।",
			"स{1}कृत् । सु । नः{1} । म{1}घ{1}{5}व{1}न् । इ{1}न्द्र{1} । मृ{1}ळ{1}य{1} । अध{2} । पि{1}ता{5}इ{2}व । नः{1} । भ{1}व{1} ॥"
		]
	},
	"sayanaBhashya" : "<p>हे शतक्रतो बहुकर्मन् मघवन्निंद्र ते तव स्तोतारं मा मां कवषं आध्यः आधयः मू- षोन यथा मूषिकाः शिश्ना स्नातानि सूत्राण्यश्नंति तथा व्यदंति विविधमदंति । तथाच यास्कः—संतपंतिमामभितः सपत्न्यइवेमाः पर्शवः कूपपर्शवोमूषिकाइवास्नातानि सूत्राणि व्यदंति स्वांगाभिधानं वास्यात् शिश्नानि व्यदंतीति वा संतपंति माध्यः कामाइति । तथा च सति हे इंद्र नोस्मान्सकृत्सुमृळयाभीष्टप्रदानेन सम्यक् सुखय अध अथ नोस्माकं पि- तेव यथा पिता तद्वद्रक्षिता भव ॥ ३ ॥</p>"
}
