{
	"id" : "7.12.2",
	"classification" : {
		"mandala" : "7",
		"sukta" : "12",
		"ashtaka" : "5",
		"adhyaya" : "2",
		"varga" : "15",
		"anuvaka" : "1",
		"rik" : "2"
	},
	"attribute" : {
		"devata" : "अग्निः",
		"rishi" : "वसिष्ठः",
		"chandas" : "त्रिष्टुप्"
	},
	"samhita" : {
		"lines" : [
			"स{0} म{1}ह्ना{0} वि{0}श्वा{2} दु{0}रि{1}ता{0}नि{2} सा{1}ह्वा{0}न{1}ग्नि{0} ष्थ{2}वे{1} द{0}म{1} आ{0} जा{1}त{0}वे{2}दाः{0}",
			"स{0} नो{2} र{0}क्षि{0}ष{0}द्दु{0}रि{1}ता{0}द{2}व{1}द्या{0}द{1}स्मा{0}न्गृ{2}ण{1}त{0} उ{1}त{0} नो{2} म{1}घो{0}नः{2}"
		]
	},
	"samhitaAux" : {
		"lines" : [
			"स म{1}ह्ना विश्वा{2} दुरि{1}तानि{2} सा{1}ह्वान{1}ग्निः ष्ट{2}वे{1} दम{1} आ जा{1}तवे{2}दाः ।",
			"स नो{2} रक्षिषद्दुरि{1}ताद{2}व{1}द्याद{1}स्मान्गृ{2}ण{1}त उ{1}त नो{2} म{1}घोनः{2} ॥"
		]
	},
	"padapaatha" : {
		"lines" : [
			"सः । म{1}ह्ना । विश्वा{2} । दुः{1}{5}इ{1}तानि{2} । सा{1}ह्वान् । अ{1}ग्निः । स्त{1}वे{1} । दमे{2} । आ । जा{1}त{5}वे{2}दाः ।",
			"सः । नः{1} । र{1}क्षि{1}ष{1}त् । दुः{1}{5}इ{1}तात् । अ{1}व{1}द्यात् । अ{1}स्मान् । गृ{1}ण{1}तः । उ{1}त । नः{1} । म{1}घोनः{2} ॥"
		]
	},
	"sayanaBhashya" : "<p>योग्निर्मह्ना महत्त्वेन विश्वा विश्वानि दुरितानि सह्वान् अभिभवन् जातवेदाः जातधनो जातप्रज्ञोवा दमे यज्ञगृहे स्तवे अस्माभिः स्तूयते सोग्निरस्मान् दुरितात् पापात् अवद्यात् निंदिताच्च कर्मणोरक्षिषत् रक्षत् । अस्मान् गृणतः स्तुवतोपि रक्षिषत् । उतापिच सोग्निः नो मघोनो हविष्मतोरक्षिषत् ॥ २ ॥</p>"
}
