{
	"id" : "8.102.11",
	"classification" : {
		"mandala" : "8",
		"sukta" : "102",
		"ashtaka" : "6",
		"adhyaya" : "7",
		"varga" : "11",
		"anuvaka" : "10",
		"rik" : "11"
	},
	"attribute" : {
		"devata" : "अग्निः",
		"rishi" : "प्रयोगो भार्गव अग्निर्वा पावको बार्हस्पत्यः, अथवाग्नी गृहपतियविष्ठौ सहसः सुतौ तयोर्वान्यतरः",
		"chandas" : "गायत्री"
	},
	"samhita" : {
		"lines" : [
			"शी॒रं पा॑व॒कशो॑चिषं॒ ज्येष्टो॒ यो दमे॒ष्वा",
			"दी॒दाय॑ दीर्घ॒श्रुत्त॑मः"
		]
	},
	"samhitaAux" : {
		"lines" : [
			"शी॒रं पा॑व॒कशो॑चिषं॒ ज्येष्ठो॒ यो दमे॒ष्वा ।",
			"दी॒दाय॑ दीर्घ॒श्रुत्त॑मः ॥"
		]
	},
	"padapaatha" : {
		"lines" : [
			"शी॒रम् । पा॒व॒कऽशो॑चिषम् । ज्येष्ठः॑ । यः । दमे॑षु । आ ।",
			"दी॒दाय॑ । दी॒र्घ॒श्रुत्ऽत॑मः ॥"
		]
	},
	"sayanaBhashya" : "<p>ज्येष्ठो देवानांमुख्यो दीर्घश्रुत्तमो अतिशयेनविद्वानग्निः दमेषु यज्जिनां गृहेषु आदीदाय आदीप्यते तं शीरं अनुशायिनम् । तथाचयास्कः-अनुशायिनमितिवा शिनमितिवेति । पावकशोचिषं पावकदीप्तिं स्तुहीत्यर्थः ॥ ११ ॥</p>"
}
