{
	"id" : "8.46.28",
	"classification" : {
		"mandala" : "8",
		"sukta" : "46",
		"ashtaka" : "6",
		"adhyaya" : "4",
		"varga" : "6",
		"anuvaka" : "6",
		"rik" : "28"
	},
	"attribute" : {
		"devata" : "वायुः",
		"rishi" : "वशोश्व्यः",
		"chandas" : "सतो बृहती"
	},
	"samhita" : {
		"lines" : [
			"उ॒च॒थ्ये॒थ्॒॑ वपु॑षि॒ यः स्व॒राळु॒त वा॑यो घृत॒स्नाः",
			"अश्वे॑षितं॒ रजे॑षितं॒ शुने॑षितं॒ प्राज्म॒ तदि॒दं नु तत्"
		]
	},
	"samhitaAux" : {
		"lines" : [
			"उ॒च॒थ्ये॒३॒॑ वपु॑षि॒ यः स्व॒राळु॒त वा॑यो घृत॒स्नाः ।",
			"अश्वे॑षितं॒ रजे॑षितं॒ शुने॑षितं॒ प्राज्म॒ तदि॒दं नु तत् ॥"
		]
	},
	"padapaatha" : {
		"lines" : [
			"उ॒च॒थ्ये॑ । वपु॑षि । यः । स्व॒ऽराट् । उ॒त । वा॒यो॒ इति॑ । घृ॒त॒ऽस्नाः ।",
			"अश्व॑ऽइषितम् । रजः॑ऽइषितम् । शुना॑ऽइषितम् । प्र । अज्म॑ । तत् । इ॒दम् । नु । तत् ॥"
		]
	},
	"sayanaBhashya" : "<p>उचथ्ये वक्तव्ये स्तुत्ये वपुषि शरीरे यःस्वराट् स्वयं राजते यद्वा उचथ्यो वपुश्चोभौराजानौ तयोरपि यः स्वराट् स्वाराज्यं करोति अतिशयेन वर्तते । उतापिच हे वायो यश्च घृतश्नाः घृतवच्छुद्धः सराजा अश्वेषितं अश्वैःप्रापितम् । रजेषितं रजःशब्देनोष्ट्रो गर्दभोवोच्यते । तेनाप्यानीतं शुनेषितंचा- ज्मान्नं प्रादात् तदन्नमश्वाद्यानीतं इदं पुरतो दृश्यते तत् तवैवानुग्रहादित्यर्थः । अथवैकस्तच्छब्दः पूरणः अश्वाद्यानीतं यदस्ति तदिदं खल्विति ॥ २८ ॥</p>"
}
