{
	"id" : "2.34.9",
	"classification" : {
		"mandala" : "2",
		"sukta" : "34",
		"ashtaka" : "2",
		"adhyaya" : "7",
		"varga" : "20",
		"anuvaka" : "4",
		"rik" : "9"
	},
	"attribute" : {
		"devata" : "मरुतः",
		"rishi" : "गृत्समद (आङ्गिरसः शौनहोत्रः पश्चाद्) भार्गवः शौनकः",
		"chandas" : "जगती"
	},
	"samhita" : {
		"lines" : [
			"यो नो॑ मरुतो वृ॒कता॑ति॒ मर्त्यो॑ रि॒पुर्द॒धे व॑सवो॒ रक्ष॑ता रि॒षः",
			"व॒र्तय॑त॒ तपु॑षा च॒क्रिया॒भि तमव॑ रुद्रा अ॒शसो॑ हन्तना॒ वधः॑"
		]
	},
	"samhitaAux" : {
		"lines" : [
			"यो नो॑ मरुतो वृ॒कता॑ति॒ मर्त्यो॑ रि॒पुर्द॒धे व॑सवो॒ रक्ष॑ता रि॒षः ।",
			"व॒र्तय॑त॒ तपु॑षा च॒क्रिया॒भि तमव॑ रुद्रा अ॒शसो॑ हन्तना॒ वधः॑ ॥"
		]
	},
	"padapaatha" : {
		"lines" : [
			"यः । नः॒ । म॒रु॒तः॒ । वृ॒कऽता॑ति । मर्त्यः॑ । रि॒पुः । द॒धे । व॒स॒वः॒ । रक्ष॑त । रि॒षः ।",
			"व॒र्तय॑त । तपु॑षा । च॒क्रिया॑ । अ॒भि । तम् । अव॑ । रु॒द्राः॒ । अ॒शसः॑ । ह॒न्त॒न॒ । वध॒रिति॑ ॥"
		]
	},
	"sayanaBhashya" : "<p>हेमरुतः योमर्त्योमनुष्यः वृकतातिआदाता वृकः वृकआदाने वृकज्येष्ठाभ्यान्तिल् तातिलौचच्छन्द सीतिस्वार्थिकस्तातिल् प्रत्ययः तादृशःसन् नोस्माकंरिपुर्दधे रिपुतयाआत्मानन्धारयति हेवसवोवास- यितारोमरुतः रिषोहिंसकादस्मान् रक्षत पालयत अस्माकंशत्रुभूतंमर्त्यन्तपुषातापयित्र्याचक्रिया ऋ- ष्ट्याख्ययाशक्त्याअभिवर्तयत अभितोनिवर्तयत हेरुद्राः रुद्रपुत्राः यद्वा रोरूयमाणाद्रवन्तः अशसो- भक्षकस्य अशभोजने इत्यस्मादौणादिकोसिप्रत्ययः तादृशस्यराक्षसादेर्वधः हननसाधनमायुधंअवह- न्तनअवयुत्यास्मत्तः पृथक् क्रुत्यनाशयत हन्तेर्लोटितप्तनप्तनथनाश्चेतितनप् ॥ ९ ॥</p>"
}
