{
	"id" : "10.150.4",
	"classification" : {
		"mandala" : "10",
		"sukta" : "150",
		"ashtaka" : "8",
		"adhyaya" : "8",
		"varga" : "8",
		"anuvaka" : "11",
		"rik" : "4"
	},
	"attribute" : {
		"devata" : "अग्निः",
		"rishi" : "मृळीको वासिष्ठः",
		"chandas" : "उपरिष्टाज्ज्योतिर्जगती वा"
	},
	"samhita" : {
		"lines" : [
			"अ{1}ग्नि{0}र्दे{1}वो{0} दे{1}वा{0}ना{2}म{0}भ{0}व{0}त्पु{1}रो{0}हि{2}तो{1}{5}ग्निं{0} म{2}नु{1}ष्या{1}थ्{1}{2} ऋ{0}ष{2}यः{1} स{0}मी{2}धि{0}रे{0}",
			"अ{1}ग्निं{0} म{1}हो{0} ध{0}न{2}सा{0}ता{0}व{1}हं{0} हु{2}वे{0} मृ{0}ळी{1}कं{0} ध{0}न{2}सा{0}त{0}ये{0}"
		]
	},
	"samhitaAux" : {
		"lines" : [
			"अ{1}ग्निर्दे{1}वो दे{1}वाना{2}मभवत्पु{1}रोहि{2}तो{1}{5}ग्निं म{2}नु{1}ष्या{1}३{2}{1} ऋष{2}य{1}ः समी{2}धिरे ।",
			"अ{1}ग्निं म{1}हो धन{2}साताव{1}हं हु{2}वे मृळी{1}कं धन{2}सातये ॥"
		]
	},
	"padapaatha" : {
		"lines" : [
			"अ{1}ग्निः । दे{1}वः । दे{1}वाना{2}म् । अ{1}भ{1}व{1}त् । पु{1}रः{5}हि{2}तः । अ{1}ग्निम् । म{1}नु{1}ष्याः{2} । ऋष{2}यः । सम् । ई{1}धि{1}रे{1} ।",
			"अ{1}ग्निम् । म{1}हः । धन{2}{5}सातौ । अ{1}हम् । हु{1}वे{1} । मृ{1}ळी{1}कम् । धन{2}{5}सातये ॥"
		]
	},
	"sayanaBhashya" : "<p>देवो दानादिगुणयुक्तोऽग्निर्देवानामन्येषां पुरोहितः पुरस्ताद्धृतोऽभवत्। यद्वा। पुरोहितवद्धितकार्यभवत्। यत एवमतः कारनात्तमेवाग्निमृषयोऽतीन्द्रियार्थदर्शिनो मनुष्या मानवा यजमानाः समीधिरे। सन्दीपयन्ति। अपि च तमग्निं महो महतो धनसातौ धनस्य सम्भजने निमित्तभूतेऽहं हुवे। आह्वये। विशेषणसापेक्षस्यापि धनशब्दस्य छान्दसः समासः। यद्वा। महतो यागस्य कर्तारमग्निमित्यर्थः। धनस्य सातये धनलाभार्थं मृळीकं सुखमेतत्संज्ञं वा मां सोऽग्निः करोत्वित्यर्थः॥४॥</p>"
}
