{
	"id" : "8.45.12",
	"classification" : {
		"mandala" : "8",
		"sukta" : "45",
		"ashtaka" : "6",
		"adhyaya" : "3",
		"varga" : "44",
		"anuvaka" : "6",
		"rik" : "12"
	},
	"attribute" : {
		"devata" : "इन्द्रः",
		"rishi" : "त्रिशोकः काण्वः",
		"chandas" : "गायत्री"
	},
	"samhita" : {
		"lines" : [
			"ऊ॒र्ध्वा हि ते॑ दि॒वेदि॑वे स॒हस्रा॑ सू॒नृता॑ श॒ता",
			"ज॒रि॒तृभ्यो॑ वि॒मंह॑ते"
		]
	},
	"samhitaAux" : {
		"lines" : [
			"ऊ॒र्ध्वा हि ते॑ दि॒वेदि॑वे स॒हस्रा॑ सू॒नृता॑ श॒ता ।",
			"ज॒रि॒तृभ्यो॑ वि॒मंह॑ते ॥"
		]
	},
	"padapaatha" : {
		"lines" : [
			"ऊ॒र्ध्वा । हि । ते॒ । दि॒वेऽदि॑वे । स॒हस्रा॑ । सू॒नृता॑ । श॒ता ।",
			"ज॒रि॒तृऽभ्यः॑ । वि॒ऽमंह॑ते ॥"
		]
	},
	"sayanaBhashya" : "<p>हे इन्द्र ते तव जरितृभ्यः स्तोतृभ्यः सहस्रा सहस्राणि शता शतानि चोर्ध्वा ऊर्ध्वानि मुख्यानि सूनृता सूनृतानि साधनानि दिवेदिवेन्वहं विमंहते यजमानः प्रयच्छति । मंहतिर्दानकर्मा ॥ १२ ॥</p>"
}
