{
	"id" : "8.13.22",
	"classification" : {
		"mandala" : "8",
		"sukta" : "13",
		"ashtaka" : "6",
		"adhyaya" : "1",
		"varga" : "11",
		"anuvaka" : "3",
		"rik" : "22"
	},
	"attribute" : {
		"devata" : "इंद्रः",
		"rishi" : "नारदः काण्वः",
		"chandas" : "उष्णिक्"
	},
	"samhita" : {
		"lines" : [
			"क{1}दा{0} त{2} इं{0}द्र{0} गि{0}र्व{0}ण{0} स्तो{1}ता{0} भ{2}वा{0}ति{1} शं{0}त{2}मः{0}",
			"क{1}दा{0} नो{1} ग{0}व्ये{1} अ{0}श्व्ये{1} व{0}सौ{2} द{0}धः{0}"
		]
	},
	"samhitaAux" : {
		"lines" : [
			"क{1}दा त{2} इन्द्र गिर्वणः स्तो{1}ता भ{2}वाति{1} शंत{2}मः ।",
			"क{1}दा नो{1} गव्ये{1} अश्व्ये{1} वसौ{2} दधः ॥"
		]
	},
	"padapaatha" : {
		"lines" : [
			"क{1}दा । ते{1} । इ{1}न्द्र{1} । गि{1}र्व{1}णः{1} । स्तो{1}ता । भ{1}वा{1}ति{1} । शम्{5}त{2}मः ।",
			"क{1}दा । नः{1} । गव्ये{2} । अश्व्ये{2} । वसौ{2} । द{1}धः{1} ॥"
		]
	},
	"sayanaBhashya" : "<p>हे गिर्वणोगिरां स्तुतीनां संभक्तरिन्द्र ते तव स्तोता शंतमः सुखतमोतिशये नसुखवान् कदा कस्मिन्काले भवाति भवेत् कदा कस्मिंश्च काले नोस्मान् गव्ये गोसमूहे अश्व्ये अश्वसंघे वसौ निवासभूतेन्यस्मिन्नपि धने दधः धारये: ॥ २२ ॥</p>"
}
