{
	"id" : "8.12.29",
	"classification" : {
		"mandala" : "8",
		"sukta" : "12",
		"ashtaka" : "6",
		"adhyaya" : "1",
		"varga" : "6",
		"anuvaka" : "2",
		"rik" : "29"
	},
	"attribute" : {
		"devata" : "इन्द्रः",
		"rishi" : "पर्वतः काण्वः",
		"chandas" : "उष्णिक्"
	},
	"samhita" : {
		"lines" : [
			"य॒दा ते॒ मारु॑ती॒र्विश॒स्तुभ्य॑मिन्द्र नियेमि॒रे",
			"आदित्ते॒ विश्वा॒ भुव॑नानि येमिरे"
		]
	},
	"samhitaAux" : {
		"lines" : [
			"य॒दा ते॒ मारु॑ती॒र्विश॒स्तुभ्य॑मिन्द्र नियेमि॒रे ।",
			"आदित्ते॒ विश्वा॒ भुव॑नानि येमिरे ॥"
		]
	},
	"padapaatha" : {
		"lines" : [
			"य॒दा । ते॒ । मारु॑तीः । विशः॑ । तुभ्य॑म् । इ॒न्द्र॒ । नि॒ऽये॒मि॒रे ।",
			"आत् । इत् । ते॒ । विश्वा॑ । भुव॑नानि । ये॒मि॒रे॒ ॥"
		]
	},
	"sayanaBhashya" : "<p>हे इन्द्र तुभ्यं त्वदर्थं मारुतीर्मारुत्यः मरुद्रूपाः ते त्वदीयाः विशः प्रजाः यदा यस्मिन्काले नियेमिरे नियच्छन्ति भूतजातानि । अन्यद्रतम् ॥ २९ ॥</p>"
}
