{
	"id" : "8.47.16",
	"classification" : {
		"mandala" : "8",
		"sukta" : "47",
		"ashtaka" : "6",
		"adhyaya" : "4",
		"varga" : "10",
		"anuvaka" : "6",
		"rik" : "16"
	},
	"attribute" : {
		"devata" : "आदित्या उषाश्च",
		"rishi" : "त्रित आप्त्यः",
		"chandas" : "महापंक्तिः"
	},
	"samhita" : {
		"lines" : [
			"त{0}द{2}न्ना{0}य{1} त{0}द{2}प{0}से{1} तं{0} भा{1}ग{0}मु{2}प{0}से{1}दु{0}षे{2}",
			"त्रि{1}ता{0}य{2} च{0} द्वि{1}ता{0}य{1} चो{0}षो{2} दु{1}ष्व{0}प्न्यं{2} व{0}हा{0}ने{1}ह{0}सो{2} व{0} ऊ{1}त{0}यः{2} सु{0}ऊ{1}त{0}यो{2} व{0} ऊ{1}त{0}यः{2}"
		]
	},
	"samhitaAux" : {
		"lines" : [
			"तद{2}न्नाय{1} तद{2}पसे{1} तं भा{1}गमु{2}पसे{1}दुषे{2} ।",
			"त्रि{1}ताय{2} च द्वि{1}ताय{1} चोषो{2} दु{1}ष्ष्वप्न्यं{2} वहाने{1}हसो{2} व ऊ{1}तयः{2} सुऊ{1}तयो{2} व ऊ{1}तयः{2} ॥"
		]
	},
	"padapaatha" : {
		"lines" : [
			"तत्{5}अ{2}न्नाय । तत्{5}अ{2}पसे । तम् । भा{1}गम् । उ{1}प{1}{5}से{1}दुषे{2} ।",
			"त्रि{1}ताय{2} । च{1} । द्वि{1}ताय{2} । च{1} । उषः{2} । दुः{1}{5}स्वप्न्य{2}म् । व{1}ह{1} । अ{1}ने{1}हसः{2} । वः{1} । ऊ{1}तयः{2} । सु{1}{5}ऊ{1}तयः{2} । वः{1} । ऊ{1}तयः{2} ॥"
		]
	},
	"sayanaBhashya" : "<p>तदन्नाय यदेव जागरावस्थायां भोज्यत्वेन प्रसिद्धं मधुपायसादि स्वप्नेपि तदेवान्नं यस्य सः तादृशाय प्रत्यक्षभोजनवत् स्वप्नेपि भोत्र्क्रे इत्यर्थः । तथा तदपसे यदेवापः कर्मनिन्दितं जाग्रदवस्थायां क्रियते तदेव कर्म स्वप्ने यस्य सतत्कर्मा तादृशाय देवाय तं भागं दुःस्वप्नत्यांशमुपसेदुषे प्राप्नुवते त्रिताय द्वितायच हे उषोदेवि दुःष्वप्न्यं अन्नकर्मविषयं वह अन्यत्र प्रापय स्वप्नेदृष्टं मधुभोजनादिकं जाग्रदवस्थानरूपवत्सुखकरं भवत्वित्यर्थः ॥ १६ ॥</p>"
}
