{
	"id" : "8.24.14",
	"classification" : {
		"mandala" : "8",
		"sukta" : "24",
		"ashtaka" : "6",
		"adhyaya" : "2",
		"varga" : "17",
		"anuvaka" : "4",
		"rik" : "14"
	},
	"attribute" : {
		"devata" : "इंद्रः",
		"rishi" : "विश्वमना वैयश्वः",
		"chandas" : "उष्णिक्"
	},
	"samhita" : {
		"lines" : [
			"उ{0}पो{1} ह{0}री{2}णां{1} प{0}तिं{1} द{0}क्षं{2} पृं{1}चं{0}त{2}म{0}ब्र{0}व{0}म्{0}",
			"नू{1}नं{0} श्रु{2}धि{0} स्तु{0}व{1}तो{0} अ{1}श्व्य{0}स्य{2}"
		]
	},
	"samhitaAux" : {
		"lines" : [
			"उपो{1} हरी{2}णां{1} पतिं{1} दक्षं{2} पृ{1}ञ्चन्त{2}मब्रवम् ।",
			"नू{1}नं श्रु{2}धि स्तुव{1}तो अ{1}श्व्यस्य{2} ॥"
		]
	},
	"padapaatha" : {
		"lines" : [
			"उपो{1} इति{2} । हरी{2}णाम् । पति{2}म् । दक्ष{2}म् । पृ{1}ञ्चन्त{2}म् । अ{1}ब्र{1}व{1}म् ।",
			"नू{1}नम् । श्रु{1}धि{1} । स्तु{1}व{1}तः । अ{1}श्व्यस्य{2} ॥"
		]
	},
	"sayanaBhashya" : "<p>हरीणां हरितवर्णानामश्वानां पतिं पालयितारं दक्षं वर्धकं स्वबलं पृंचन्तं पृचीसंपर्के मरुत्सु योजयन्तम् यद्वा शत्रुषु स्वबलमायुधादिभिः संपर्चयन्त- मेतादृशमिन्द्रं त्वामुपो अब्रवं विश्वमना अहं स्तोत्रं करवाणि । अश्व्यस्य व्यश्वोनामर्षिः अश्वशब्देनोच्यते तस्य पुत्रस्य स्तुवतः स्तोत्रं कुर्वतोमम संबन्धिनीं त्वद्विषयां स्तुतिं नूनं सम्प्रति श्रुधि शृणु ॥ १४ ॥</p>"
}
