{
	"id" : "7.104.3",
	"classification" : {
		"mandala" : "7",
		"sukta" : "104",
		"ashtaka" : "5",
		"adhyaya" : "7",
		"varga" : "5",
		"anuvaka" : "6",
		"rik" : "3"
	},
	"attribute" : {
		"devata" : "इंद्रासोमौ रक्षोहणौ",
		"rishi" : "वसिष्ठः",
		"chandas" : "जगती"
	},
	"samhita" : {
		"lines" : [
			"इं{0}द्रा{2}सो{0}मा{0} दु{1}ष्कृ{0}तो{2} व{1}व्रे{0} अं{1}त{0}र{2}ना{0}रं{0}भ{1}णे{0} त{0}म{2}सि{1} प्र{0} वि{2}ध्य{0}त{0}म्{0}",
			"य{0}था{1} ना{0}तः{1} पु{0}न{1}रे{0}क{2}श्च{1}नो{0}द{0}य{1}त्त{0}द्वा{2}म{0}स्तु{1} स{0}ह{2}से{0} म{0}न्यु{1}म{0}च्छ{0}वः{2}"
		]
	},
	"samhitaAux" : {
		"lines" : [
			"इन्द्रा{2}सोमा दु{1}ष्कृतो{2} व{1}व्रे अ{1}न्तर{2}नारम्भ{1}णे तम{2}सि{1} प्र वि{2}ध्यतम् ।",
			"यथा{1} नात{1}ः पुन{1}रेक{2}श्च{1}नोदय{1}त्तद्वा{2}मस्तु{1} सह{2}से मन्यु{1}मच्छवः{2} ॥"
		]
	},
	"padapaatha" : {
		"lines" : [
			"इन्द्रा{2}सोमा । दुः{1}{5}कृतः{2} । व{1}व्रे । अ{1}न्तः । अ{1}ना{1}र{1}म्भ{1}णे । तम{2}सि । प्र । वि{1}ध्य{1}त{1}म् ।",
			"यथा{2} । न । अतः{2} । पुनः{2} । एकः{2} । च{1}न । उ{1}त्{5}अय{2}त् । तत् । वा{1}म् । अ{1}स्तु{1} । सह{2}से । म{1}न्यु{1}{5}मत् । शवः{2} ॥"
		]
	},
	"sayanaBhashya" : "<p>हे इन्द्रासोमौ दुष्कृतः दुष्कर्मकारिणो राक्षसान् वव्रे वारके अन्तर्मध्ये अनारंभणे आलंबनरहिते तमस्यन्धकारे प्रविध्यतं प्रवेश्य ताडयतम् यथा येनप्रकारेण एषां मध्ये एकश्चन एकोपि राक्षसः अतः अस्मात्तमसः पुनर्नोदयत् उद्गच्छेत् तथा विध्यतमित्यर्थः । एतेर्लेट्यडागमः इतश्चलोपइतीकारलोपः गुणायादेशौ । तत्प्रसिद्धम् मन्युमत् क्रोधयुक्तं वां युवयोः शवोबलं सहसे रक्षसामभि- भवनाय अस्तु भवतु ॥ ३ ॥</p>"
}
