{
	"id" : "5.28.6",
	"classification" : {
		"mandala" : "5",
		"sukta" : "28",
		"ashtaka" : "4",
		"adhyaya" : "1",
		"varga" : "22",
		"anuvaka" : "2",
		"rik" : "6"
	},
	"attribute" : {
		"devata" : "अग्निः",
		"rishi" : "विश्ववारात्रेयी",
		"chandas" : "गायत्री"
	},
	"samhita" : {
		"lines" : [
			"आ जु॑होता दुव॒स्यता॒ग्निं प्र॑य॒त्य॑ध्व॒रे",
			"वृ॒णी॒ध्वं ह॑व्य॒वाह॑नम्"
		]
	},
	"samhitaAux" : {
		"lines" : [
			"आ जु॑होता दुव॒स्यता॒ग्निं प्र॑य॒त्य॑ध्व॒रे ।",
			"वृ॒णी॒ध्वं ह॑व्य॒वाह॑नम् ॥"
		]
	},
	"padapaatha" : {
		"lines" : [
			"आ । जु॒हो॒त॒ । दु॒व॒स्यत॑ । अ॒ग्निम् । प्र॒ऽय॒ति । अ॒ध्व॒रे ।",
			"वृ॒णी॒ध्वम् । ह॒व्य॒ऽवाह॑नम् ॥"
		]
	},
	"sayanaBhashya" : "<p>हेऋत्विजोयूयं अध्वरे अस्मदीयेयागे प्रयति प्रवृत्तेसति हव्यवाहनं हविषांवोढारं एतन्नामकमाग्निं आजुहोत आसमन्ताज्जुहोत तथा दुवस्यत परिचरत व्रणीध्वंसंभजध्वंच हव्यवाहनंहव्यवाहननामकस्यैवाग्नेर्देवतासंबन्धोयजमानैर्वरणीयत्वंचतैत्तिरीयेस्पष्टमाम्नातं-त्रयोवाअग्नयोहव्यवाहनोदेवानाङ्कव्यवाहनः पितॄणांसहरक्षाअसुराणान्तएतर्ह्याशंसन्तेमावरिष्यतेमामिति । वृणीध्वंहव्यवाहनमित्याहय -एवदेवानान्तंवृणीतइति ॥ ६ ॥</p><p class=\"end\">त्र्यर्यमेतिपंचदशर्चंपंचदशंसूक्तं अत्रानुक्रमणिका-त्र्यर्यमापंचोनागौरिवीतिः शाक्त्यऎन्द्रमुशनायदौशनसौवापादइति । शक्तिगोत्रोत्पन्नोगौरिवीतिर्नामऋषिः अनुक्तत्वान्त्रिष्टुप् इन्द्रोदेवता मंडलादिपरिभाषयानिवृत्तत्वात् उशनायत्सहस्यैरितिपादऔशनसः ऎन्द्रोवा आभिप्लविकेतृतीयेहनिमरुत्वतीयेएतन्निविद्धानं सूत्रितंच-तृतीयस्यत्र्यर्यमायोजातएवेतिमाध्यन्दिनइति ।</p>"
}
