{
	"id" : "3.50.4",
	"classification" : {
		"mandala" : "3",
		"sukta" : "50",
		"ashtaka" : "3",
		"adhyaya" : "3",
		"varga" : "14",
		"anuvaka" : "4",
		"rik" : "4"
	},
	"attribute" : {
		"devata" : "इंद्रः",
		"rishi" : "गाथिनो विश्वामित्रः",
		"chandas" : "त्रिष्टुप्"
	},
	"samhita" : {
		"lines" : [
			"इ{1}मं{0} का{0}मं{2} मं{0}द{0}या{1} गो{0}भि{1}र{0}श्वै{2}श्चं{1}द्र{0}व{2}ता{1} रा{0}ध{2}सा{0} प{1}प्र{0}थ{2}श्च{0}",
			"स्व{1}र्य{0}वो{2} म{1}ति{0}भि{1}स्तु{0}भ्यं{1} वि{0}प्रा{1} इं{0}द्रा{2}य{1} वा{0}हः{2} कु{0}शि{1}का{0}सो{2} अ{0}क्र{0}न्{0}"
		]
	},
	"samhitaAux" : {
		"lines" : [
			"इ{1}मं कामं{2} मन्दया{1} गोभि{1}रश्वै{2}श्च{1}न्द्रव{2}ता{1} राध{2}सा प{1}प्रथ{2}श्च ।",
			"स्व{1}र्यवो{2} म{1}तिभि{1}स्तुभ्यं{1} विप्रा{1} इन्द्रा{2}य{1} वाहः{2} कुशि{1}कासो{2} अक्रन् ॥"
		]
	},
	"padapaatha" : {
		"lines" : [
			"इ{1}मम् । काम{2}म् । म{1}न्द{1}य{1} । गोभिः{2} । अश्वैः{2} । च{1}न्द्र{5}व{2}ता । राध{2}सा । प{1}प्रथः{2} । च{1} ।",
			"स्वः{1}{5}यवः{2} । म{1}ति{5}भिः{2} । तुभ्य{2}म् । विप्राः{2} । इन्द्रा{2}य । वाहः{2} । कु{1}शि{1}कासः{2} । अ{1}क्र{1}न् ॥"
		]
	},
	"sayanaBhashya" : "<p>हे इन्द्र इमं धनादिविषयं काममस्मदीयमभिलाषं गोभिरग्निहोत्रादिकर्मसाधनभुतैर्गवादिभिर्वाहनसाधनभूतैरश्वैश्च चन्द्रवता दीप्तियुक्तेन राधसा धनेन च मन्दय । एतानि दत्त्वेममभिलाषं पूरय । किञ्च । एतैरस्मान्पप्रथः । प्रथितांश्च कुरु । पश्चात्स्वर्यवः स्वर्गाअदिसुखमात्मन इच्छन्तो विप्राः कर्मकुशलाः कुशिकासः कुशिका मतिभिर्मननीयैर्मन्त्रैर्वाहः स्तोत्रमिन्द्राय तुभ्यमक्रन् । अकार्षुः । मन्दय । मदि स्तुत्यादिष्वित्यस्य लोटि रूपम् । गोभिः । सावेकाच इति विभक्तेरुदात्तत्वे प्राप्ते न गोश्वन्साववर्णेत्यादिना प्रतिषेधः । प्रकृतिस्वरः । पप्रथः । प्रथप्रख्याने । क्विप् । डन्दस्युभयथेति तस्य सार्वधातुकत्वात् शप् । तस्य बहुलं छन्दसिति श्लुः । धातुस्वरः । अक्रन् । करोतेर्लुङि मन्त्रे घसह्वरेत्यादिना लुक् । निघातः ॥ ४ ॥</p>"
}
