{
	"id" : "3.56.7",
	"classification" : {
		"mandala" : "3",
		"sukta" : "56",
		"ashtaka" : "3",
		"adhyaya" : "4",
		"varga" : "1",
		"anuvaka" : "5",
		"rik" : "7"
	},
	"attribute" : {
		"devata" : "विश्वेदेवाः",
		"rishi" : "प्रजापतिर्वैश्वामित्रः प्रजापतिर्वाच्यो वा",
		"chandas" : "त्रिष्टुप्"
	},
	"samhita" : {
		"lines" : [
			"त्रि{0}रा{0} दि{1}वः{0} स{2}वि{1}ता{0} सो{2}ष{0}वी{0}ति{1} रा{0}जा{2}ना{0} मि{1}त्रा{0}व{0}रु{2}णा{0} सु{0}पा{1}णी{0}",
			"आ{0}प{2}श्चि{0}द{0}स्य{1} रो{0}द{2}सी{0} चि{0}दु{1}र्वि{0} र{0}त्नं{2} भि{0}क्षं{0}त{0} स{0}वि{1}तुः{0} स{1}वा{0}य{2}"
		]
	},
	"samhitaAux" : {
		"lines" : [
			"त्रिरा दि{1}वः स{2}वि{1}ता सो{2}षवीति{1} राजा{2}ना मि{1}त्रावरु{2}णा सुपा{1}णी ।",
			"आप{2}श्चिदस्य{1} रोद{2}सी चिदु{1}र्वी रत्नं{2} भिक्षन्त सवि{1}तुः स{1}वाय{2} ॥"
		]
	},
	"padapaatha" : {
		"lines" : [
			"त्रिः । आ । दि{1}वः । स{1}वि{1}ता । सो{1}ष{1}वी{1}ति{1} । राजा{2}ना । मि{1}त्रावरु{2}णा । सु{1}पा{1}णी इति{2} सु{1}{5}पा{1}णी ।",
			"आपः{2} । चि{1}त् । अ{1}स्य{1} । रोद{2}सी{1} इति{2} । चि{1}त् । उ{1}र्वी इति{2} । रत्न{2}म् । भि{1}क्ष{1}न्त{1} । स{1}वि{1}तुः । स{1}वाय{2} ॥"
		]
	},
	"sayanaBhashya" : "<p>सविता देवो दिवो दिवसस्य त्रिस्त्रिषु कालेष्वा सोषवीति । अस्मभ्यं धनान्यासुवतु । प्रेरयतु । किञ्च राजाना राजानौ सुपाणी कल्याणपाणी मित्रावरुणावापः । आप्नोति सर्वं जगदित्याप अन्तरिक्षम् । नित्यबहुवचनान्तत्वाद्बहुवचनम् । चिदपि च उर्वी विस्तीर्णे रोदसी द्यावापृथिव्यावेता देवताः सवितुः प्रेरकस्यास्य देवस्य सवाय सवेन प्रेरणेन रत्नमपेक्षितमर्थं भिक्षन्त । याचन्ते ॥ सोसवीति । षू प्रेरण इत्यस्य यङ्लुकि लटि रूपम् । मित्रावरुणा । देवताद्वन्द्वे चेत्युभयपदप्रकृतिस्वरत्वम् । भिक्षन्त । भिक्ष यज्ञायामित्यस्य लङिरूपम् । सवाय । जवसवौ च । पा. ३-३-५६-४ ॥ इत्यजन्तत्वेन निपातनादन्तोदात्तत्वं ॥ ७ ॥</p>"
}
