{
	"id" : "5.32.1",
	"classification" : {
		"mandala" : "5",
		"sukta" : "32",
		"ashtaka" : "4",
		"adhyaya" : "1",
		"varga" : "32",
		"anuvaka" : "2",
		"rik" : "1"
	},
	"attribute" : {
		"devata" : "इन्द्रः",
		"rishi" : "गातुरात्रेयः",
		"chandas" : "त्रिष्टुप्"
	},
	"samhita" : {
		"lines" : [
			"अद॑र्द॒रुत्स॒मसृ॑जो॒ वि खानि॒ त्वम॑र्ण॒वान्ब॑द्बधा॒नाँ अ॑रम्णाः",
			"म॒हान्त॑मिन्द्र॒ पर्व॑तं॒ वि यद्वः सृ॒जो वि धारा॒ अव॑ दान॒वं ह॑न्"
		]
	},
	"samhitaAux" : {
		"lines" : [
			"अद॑र्द॒रुत्स॒मसृ॑जो॒ वि खानि॒ त्वम॑र्ण॒वान्ब॑द्बधा॒नाँ अ॑रम्णाः ।",
			"म॒हान्त॑मिन्द्र॒ पर्व॑तं॒ वि यद्वः सृ॒जो वि धारा॒ अव॑ दान॒वं ह॑न् ॥"
		]
	},
	"padapaatha" : {
		"lines" : [
			"अद॑र्दः । उत्स॑म् । असृ॑जः । वि । खानि॑ । त्वम् । अ॒र्ण॒वान् । ब॒द्ब॒धा॒नान् । अ॒र॒म्णाः॒ ।",
			"म॒हान्त॑म् । इ॒न्द्र॒ । पर्व॑तम् । वि । यत् । वरिति॒ वः । सृ॒जः । वि । धाराः॑ । अव॑ । दा॒न॒वम् । ह॒न्निति॑ हन् ॥"
		]
	},
	"sayanaBhashya" : "<p>हेइन्द्र त्वं उत्सं उत्स्यन्दमानंमेघं अदर्दः विदारितवानसि तदनन्तरं खानि मेघस्थोदकानान्निर्गमनद्वाराणि व्यसृजः विशेषेणसृष्टवानसि किंच वद्बधानान् बाध्यमानान् अर्णवान् उदकवतोमेघान् अरम्णाः विसर्जयसि क्षारयसीत्यर्थः अत्ररम्णातिविसर्जनकर्मा हेइन्द्र यत् यस्त्वं यदितिलिङ्गव्यत्ययः महान्तंप्रभूतंपवर्तंमेघं विवः विवृतवानसि धाराः अपांविसृजः विसृष्टवानसि अपिच दानवं दनोःपुत्रं वृत्रमसुरं यद्वा उदकस्यदातारंमेघंवा अवहन् अभिहतवानसि अत्रनिरुक्तम्-अदृणाउत्समुत्सउत्सदनाद्वोत्स्यन्दना द्वोनत्तेर्वास्या -द्भ्यसृजोस्यखानित्व- मर्णवानर्णस्वतएतानित्यादि ॥ १ ॥</p>"
}
