{
	"id" : "8.53.1",
	"classification" : {
		"mandala" : "8",
		"sukta" : "53",
		"ashtaka" : "6",
		"adhyaya" : "4",
		"varga" : "22",
		"anuvaka" : "6",
		"rik" : "1"
	},
	"attribute" : {
		"devata" : "इन्द्रः",
		"rishi" : "मेध्यः काण्वः",
		"chandas" : "बृहती"
	},
	"samhita" : {
		"lines" : [
			"उ॒प॒मं त्वा॑ म॒घोनां॒ ज्येष्टं॑ च वृष॒भाणा॑म्",
			"पू॒र्भित्त॑मं मघवन्निन्द्र गो॒विद॒मीशा॑नं रा॒य ई॑महे"
		]
	},
	"samhitaAux" : {
		"lines" : [
			"उ॒प॒मं त्वा॑ म॒घोनां॒ ज्येष्ठं॑ च वृष॒भाणा॑म् ।",
			"पू॒र्भित्त॑मं मघवन्निन्द्र गो॒विद॒मीशा॑नं रा॒य ई॑महे ॥"
		]
	},
	"padapaatha" : {
		"lines" : [
			"उ॒प॒ऽमम् । त्वा॒ । म॒घोना॑म् । ज्येष्ठ॑म् । च॒ । वृ॒ष॒भाणा॑म् ।",
			"पू॒र्भित्ऽत॑मम् । म॒घ॒ऽव॒न् । इ॒न्द्र॒ । गो॒ऽविद॑म् । ईशा॑नम् । रा॒यः । ई॒म॒हे॒ ॥"
		]
	},
	"sayanaBhashya" : "<p>Sayana bhashya empty</p>"
}
