{
	"id" : "9.107.22",
	"classification" : {
		"mandala" : "9",
		"sukta" : "107",
		"ashtaka" : "7",
		"adhyaya" : "5",
		"varga" : "16",
		"anuvaka" : "7",
		"rik" : "22"
	},
	"attribute" : {
		"devata" : "पवमानः सोमः",
		"rishi" : "सप्तर्षयः(ट् भरद्वाजो बार्हस्पत्यः, ढ् कश्यपो मारीचः, थ् गोतमो राहूगणः, ध् भौमोत्रिः, श् विश्वामित्रो गाथिनः, ६ जमदग्निर्भार्गवः, ७ मैत्रावरुणिर्वसिष्ठः)",
		"chandas" : "सतो बृहती"
	},
	"samhita" : {
		"lines" : [
			"मृ॒जा॒नो वारे॒ पव॑मानो अ॒व्यये॒ वृषाव॑ चक्रदो॒ वने॑",
			"दे॒वानां॑ सोम पवमान निष्कृ॒तं गोभि॑रंजा॒नो अ॑र्षसि"
		]
	},
	"samhitaAux" : {
		"lines" : [
			"मृ॒जा॒नो वारे॒ पव॑मानो अ॒व्यये॒ वृषाव॑ चक्रदो॒ वने॑ ।",
			"दे॒वानां॑ सोम पवमान निष्कृ॒तं गोभि॑रञ्जा॒नो अ॑र्षसि ॥"
		]
	},
	"padapaatha" : {
		"lines" : [
			"मृ॒जा॒नः । वारे॑ । पव॑मानः । अ॒व्यये॑ । वृषा॑ । अव॑ । च॒क्र॒दः॒ । वने॑ ।",
			"दे॒वाना॑म् । सो॒म॒ । प॒व॒मा॒न॒ । निः॒ऽकृ॒तम् । गोभिः॑ । अ॒ञ्जा॒नः । अ॒र्ष॒सि॒ ॥"
		]
	},
	"sayanaBhashya" : "<p>हे सोम वृषा वर्षिता त्वं मृजानः वसतीवरीभिर्मृज्यमानः अलङ्क्रियमाणः अव्यये अवि मये वारे वाले पवित्रे पवमानः पूयमानः सन् वने वननीये उदके काष्ठे कलशेवा अव- चक्रदः अवक्रन्दसि शब्दायसे । ततो हो सोमः हे पवमान त्वं गोभिर्गव्यैः क्षीरादिभिः अंजानः अज्यमानः सन् निःकृतं संस्कृतं देवानां स्थानं अर्षसि गच्छसि ॥ २२ ॥</p>"
}
