{
	"id" : "8.98.5",
	"classification" : {
		"mandala" : "8",
		"sukta" : "98",
		"ashtaka" : "6",
		"adhyaya" : "7",
		"varga" : "1",
		"anuvaka" : "10",
		"rik" : "5"
	},
	"attribute" : {
		"devata" : "इन्द्रः",
		"rishi" : "नृमेधः",
		"chandas" : "उष्णिक्"
	},
	"samhita" : {
		"lines" : [
			"अ॒भि हि स॑त्य सोमपा उ॒भे ब॒भूथ॒ रोद॑सी",
			"इन्द्रासि॑ सुन्व॒तो वृ॒धः पति॑र्दि॒वः"
		]
	},
	"samhitaAux" : {
		"lines" : [
			"अ॒भि हि स॑त्य सोमपा उ॒भे ब॒भूथ॒ रोद॑सी ।",
			"इन्द्रासि॑ सुन्व॒तो वृ॒धः पति॑र्दि॒वः ॥"
		]
	},
	"padapaatha" : {
		"lines" : [
			"अ॒भि । हि । स॒त्य॒ । सो॒म॒ऽपाः॒ । उ॒भे इति॑ । ब॒भूथ॑ । रोद॑सी॒ इति॑ ।",
			"इन्द्र॑ । असि॑ । सु॒न्व॒तः । वृ॒धः । पतिः॑ । दि॒वः ॥"
		]
	},
	"sayanaBhashya" : "<p>हे सत्य सोमपाः सोमस्य पातरिन्द्र यस्त्वं उभे रोदसी द्यावापृथिव्यौ अभि बभूथ सामर्थ्येनाभिभवसि सत्वं सुन्वतः सोमाभिषवं कुर्वतो यजमानस्य वृधोवर्धकोसि दिवः स्वर्गस्यापि पतिरीश्वरोसि ॥ ५ ॥</p>"
}
