{
	"id" : "7.91.4",
	"classification" : {
		"mandala" : "7",
		"sukta" : "91",
		"ashtaka" : "5",
		"adhyaya" : "6",
		"varga" : "13",
		"anuvaka" : "6",
		"rik" : "4"
	},
	"attribute" : {
		"devata" : "इंद्रवायू",
		"rishi" : "वसिष्ठः",
		"chandas" : "त्रिष्टुप्"
	},
	"samhita" : {
		"lines" : [
			"या{0}व{1}त्त{0}र{2}स्त{1}न्वो{1}थ्{1}{2} या{0}व{1}दो{0}जो{1} या{0}व{1}न्न{0}र{1}श्च{0}क्ष{2}सा{1} दी{0}ध्या{2}नाः{0}",
			"शु{0}चिं{1} सो{0}मं{2} शु{0}चि{0}पा{0} पा{0}त{0}म{1}स्मे{0} इं{0}द्र{2}वा{0}यू{1} स{0}द{2}तं{0} ब{1}र्हि{0}रे{0}द{0}म्{0}"
		]
	},
	"samhitaAux" : {
		"lines" : [
			"याव{1}त्तर{2}स्त{1}न्वो{1}३{2}{1} याव{1}दोजो{1} याव{1}न्नर{1}श्चक्ष{2}सा{1} दीध्या{2}नाः ।",
			"शुचिं{1} सोमं{2} शुचिपा पातम{1}स्मे इन्द्र{2}वायू{1} सद{2}तं ब{1}र्हिरेदम् ॥"
		]
	},
	"padapaatha" : {
		"lines" : [
			"याव{2}त् । तरः{2} । त{1}न्वः{2} । याव{2}त् । ओजः{2} । याव{2}त् । नरः{2} । चक्ष{2}सा । दीध्या{2}नाः ।",
			"शुचि{2}म् । सोम{2}म् । शु{1}चि{1}{5}पा{1} । पा{1}त{1}म् । अ{1}स्मे इति{2} । इन्द्र{2}वायू{1} इति{2} । सद{2}तम् । ब{1}र्हिः । आ । इ{1}दम् ॥"
		]
	},
	"sayanaBhashya" : "<p>हे इन्द्रवायू युवयोस्तन्वः शरीरस्य तरो वेगो यावदस्ति यावच्च ओजो बलं यावच्च नरः कर्मणां नेतार ऋत्विजः चक्षसा ज्ञानेन दीध्यानाः दीप्यमानाः भवन्ति तस्य सर्वस्यानुरूपं शुचिपा शुचेः सोमस्य पाताराविन्द्रवायू शुचिंशुद्धं सोमं अस्मे अस्मदीयं पातं पिबतम् । इदं वेद्यां स्तीर्णं बर्हिश्च आसदतं पानार्थमासीदतं बर्हिषि उपविशतमित्यर्थः ॥ ४ ॥</p>"
}
