{
	"id" : "8.52.7",
	"classification" : {
		"mandala" : "8",
		"sukta" : "52",
		"ashtaka" : "6",
		"adhyaya" : "4",
		"varga" : "21",
		"anuvaka" : "6",
		"rik" : "7"
	},
	"attribute" : {
		"devata" : "इंद्रः",
		"rishi" : "आयुः काण्वः",
		"chandas" : "बृहती"
	},
	"samhita" : {
		"lines" : [
			"क{1}दा{0} च{1}न{0} प्र{0} यु{2}च्छ{0}स्यु{1}भे{0} नि{0} पा{2}सि{1} ज{0}न्म{2}नी{0}",
			"तु{0}री{2}या{0}दि{0}त्य{1} ह{0}व{2}नं{0} त{0} इं{0}द्रि{1}य{0}मा{0} त{2}स्था{0}व{1}मृ{0}तं{2} दि{1}वि{0}"
		]
	},
	"samhitaAux" : {
		"lines" : [
			"क{1}दा च{1}न प्र यु{2}च्छस्यु{1}भे नि पा{2}सि{1} जन्म{2}नी ।",
			"तुरी{2}यादित्य{1} हव{2}नं त इन्द्रि{1}यमा त{2}स्थाव{1}मृतं{2} दि{1}वि ॥"
		]
	},
	"padapaatha" : {
		"lines" : [
			"क{1}दा । च{1}न । प्र । यु{1}च्छ{1}सि{1} । उ{1}भे इति{2} । नि । पा{1}सि{1} । जन्म{2}नी{1} इति{2} ।",
			"तुरी{2}य । आ{1}दि{1}त्य{1} । हव{2}नम् । ते{1} । इ{1}न्द्रि{1}यम् । आ । त{1}स्थौ{1} । अ{1}मृत{2}म् । दि{1}वि ॥"
		]
	},
	"sayanaBhashya" : "<p>Sayana bhashya empty</p>"
}
