{
	"id" : "1.66.3",
	"classification" : {
		"mandala" : "1",
		"sukta" : "66",
		"ashtaka" : "1",
		"adhyaya" : "5",
		"varga" : "10",
		"anuvaka" : "12",
		"rik" : "3"
	},
	"attribute" : {
		"devata" : "अग्निः",
		"rishi" : "पराशरः शाक्त्यः",
		"chandas" : "द्विपदा विराट्"
	},
	"samhita" : {
		"lines" : "दा{1}धा{0}र{1} क्षे{0}म{1}मो{0}को{1} न{0} र{1}ण्वो{0} य{0}वो{1} न{0} प{1}क्वो{0} जे{0}ता{1} ज{0}ना{2}ना{0}म्{0}"
	},
	"samhitaAux" : {
		"lines" : "दा{1}धार{1} क्षेम{1}मोको{1} न र{1}ण्वो यवो{1} न प{1}क्वो जेता{1} जना{2}नाम् ॥"
	},
	"padapaatha" : {
		"lines" : "दा{1}धार{2} । क्षेम{2}म् । ओकः{2} । न । र{1}ण्वः । यवः{2} । न । प{1}क्वः । जेता{2} । जना{2}नाम् ॥"
	},
	"sayanaBhashya" : "<p>Sayana bhashya empty</p>"
}
