{
	"id" : "10.34.7",
	"classification" : {
		"mandala" : "10",
		"sukta" : "34",
		"ashtaka" : "7",
		"adhyaya" : "8",
		"varga" : "4",
		"anuvaka" : "3",
		"rik" : "7"
	},
	"attribute" : {
		"devata" : "अक्षकृषिप्रशंसा",
		"rishi" : "कवष ऐलूषो अक्षो वा मौजवान्",
		"chandas" : "जगती"
	},
	"samhita" : {
		"lines" : [
			"अ॒क्षास॒ इदं॑कु॒शिनो॑ नितो॒दिनो॑ नि॒कृत्वा॑न॒स्तप॑नास्तापयि॒ष्णवः॑",
			"कु॒मा॒रदे॑ष्णा॒ जय॑तः पुन॒र्हणो॒ मध्वा॒ संपृ॑क्ताः कित॒वस्य॑ ब॒र्हणा॑"
		]
	},
	"samhitaAux" : {
		"lines" : [
			"अ॒क्षास॒ इद॑ङ्कु॒शिनो॑ नितो॒दिनो॑ नि॒कृत्वा॑न॒स्तप॑नास्तापयि॒ष्णवः॑ ।",
			"कु॒मा॒रदे॑ष्णा॒ जय॑तः पुन॒र्हणो॒ मध्वा॒ सम्पृ॑क्ताः कित॒वस्य॑ ब॒र्हणा॑ ॥"
		]
	},
	"padapaatha" : {
		"lines" : [
			"अ॒क्षासः॑ । इत् । अ॒ङ्कु॒शिनः॑ । नि॒ऽतो॒दिनः॑ । नि॒ऽकृत्वा॑नः । तप॑नाः । ता॒प॒यि॒ष्णवः॑ ।",
			"कु॒मा॒रऽदे॑ष्णाः । जय॑तः । पु॒नः॒ऽहनः॑ । मध्वा॑ । सम्ऽपृ॑क्ताः । कि॒त॒वस्य॑ । ब॒र्हणा॑ ॥"
		]
	},
	"sayanaBhashya" : "<p>अक्षासइत् अक्षाएव अङ्कुशिनोङ्कुशवन्तोनितोदिनोनितोदितवन्तश्च पुरुषे च कृषौ प्रवर्त माने निकृत्वानः पराजये निकर्तनशीलाः छेत्तारोवा तपनाः पराजये कित्वस्य सन्तापकाः तापयिष्णवः सर्वस्वहारकत्वेन कुटुंबस्य सन्तापनशीलाश्च भवन्ति । किंच जयतः कितवस्य कुमारदेष्णाधनदानेन धन्यतां लंभयन्तः कुमाराणां दातारोभवन्ति । अपिच मध्वा मधुना संपृक्ताः प्रतिकितवेन बर्हणा परिवृद्धेन सर्वस्वहरणेन कितवस्य पुनर्हणः पुनर्हन्तारोभवन्ति ॥ ७ ॥</p>"
}
