{
	"id" : "9.67.1",
	"classification" : {
		"mandala" : "9",
		"sukta" : "67",
		"ashtaka" : "7",
		"adhyaya" : "2",
		"varga" : "13",
		"anuvaka" : "3",
		"rik" : "1"
	},
	"attribute" : {
		"devata" : "पवमानः सोमः",
		"rishi" : "भरद्वाजः",
		"chandas" : "गायत्री"
	},
	"samhita" : {
		"lines" : [
			"त्वं{0} सो{2}मा{0}सि{0} धा{0}र{1}यु{0}र्मं{1}द्र{0}ओ{0}जि{2}ष्टो{0} अ{0}ध्व{1}रे{0}",
			"प{0}व{2}स्व{0} मं{0}ह{1}य{0}द्र{2}यिः{0}"
		]
	},
	"samhitaAux" : {
		"lines" : [
			"त्वं सो{2}मासि धार{1}युर्म{1}न्द्र ओजि{2}ष्ठो अध्व{1}रे ।",
			"पव{2}स्व मंह{1}यद्र{2}यिः ॥"
		]
	},
	"padapaatha" : {
		"lines" : [
			"त्वम् । सो{1}म{1} । अ{1}सि{1} । धा{1}र{1}युः । म{1}न्द्रः । ओजि{2}ष्ठः । अ{1}ध्व{1}रे ।",
			"पव{2}स्व । मं{1}ह{1}यत्{5}र{2}यिः ॥"
		]
	},
	"sayanaBhashya" : "<p>हे सोमाभिषूयमाण पवमान मन्द्रः मोदयितृतमः ओजिष्ठः ओजस्वितमस्त्वं अध्वरे हिं- सारहितेस्मदीयेयज्ञे धारयुः अभिषवणधाराकामोसि भवसि । अतस्त्वं मंहयद्रयिः स्तोतृभ्यः प्रदीयमानधनः सन् पवस्व द्रोणकलशे ग्रहादिषु दशापवित्रेण पूतोभव । यद्वा धारयुः तद्वद- र्थेभाष्यतइति सत्वर्थीयोयुः सः हे सोम त्वं धारावानिव । ततः पवस्वेति संबन्धः ॥ १ ॥</p>"
}
